ralf/__init__.py
ralf/classifier.py
ralf/config.yml
ralf/dispatcher.py
ralf/utils.py
ralf_jhuapl-0.0.6.dist-info/LICENSE
ralf_jhuapl-0.0.6.dist-info/WHEEL
ralf_jhuapl-0.0.6.dist-info/METADATA
ralf_jhuapl-0.0.6.dist-info/RECORD
