Metadata-Version: 2.1
Name: ralf-jhuapl
Version: 0.0.6
Summary: A lightweight library to support the development of applications using LLMs.
Author-email: JHUAPL <ralf@jhuapl.edu>
Requires-Python: >=3.9
Classifier: Programming Language :: Python :: 3
Classifier: Operating System :: OS Independent
Classifier: License :: OSI Approved :: MIT License
Requires-Dist: openai
Requires-Dist: numpy
Requires-Dist: PyYAML
Requires-Dist: sentence-transformers
Requires-Dist: tiktoken
Project-URL: Documentation, https://ralf-test.readthedocs.io/en/latest/
Project-URL: Source, https://github.com/jhuapl-fomo/ralf
